fatty_acylizer/__init__.py
fatty_acylizer/models/__init__.py
fatty_acylizer/models/basic.py
fatty_acylizer/models/cached.py
fatty_acylizer/models/gradient.py
fatty_acylizer/models/memo.py
fatty_acylizer/util/__init__.py
fatty_acylizer/util/combinatorics.py
fatty_acylizer/util/feature.py
fatty_acylizer/util/model.py
fatty_acylizer/util/optimization.py
fatty_acylizer/util/suggestion.py
fatty_acylizer/util/serializer/__init__.py
fatty_acylizer/util/serializer/csv.py
fatty_acylizer/util/serializer/debug_ser.py
fatty_acylizer-0.4.2.dist-info/LICENSE
fatty_acylizer-0.4.2.dist-info/METADATA
fatty_acylizer-0.4.2.dist-info/WHEEL
fatty_acylizer-0.4.2.dist-info/top_level.txt
fatty_acylizer-0.4.2.dist-info/RECORD
