Metadata-Version: 2.2
Name: fatty-acylizer
Version: 0.4.2
Summary: Mathematical remodeling model
Author-email: Janik Kokot <janik.kokot@i-med.ac.at>
License: MIT License
Requires-Python: >=3.11
License-File: LICENSE
Requires-Dist: numpy
Requires-Dist: scipy
Requires-Dist: scikit-learn
Provides-Extra: dev
Requires-Dist: pytest; extra == "dev"
Requires-Dist: pytest-cov; extra == "dev"
Requires-Dist: pre-commit; extra == "dev"
Requires-Dist: mypy; extra == "dev"
Requires-Dist: ruff; extra == "dev"
Requires-Dist: pyperf; extra == "dev"
Requires-Dist: icecream; extra == "dev"
Requires-Dist: memory_profiler; extra == "dev"
Provides-Extra: extra
Requires-Dist: pyarrow; extra == "extra"
Requires-Dist: pandas; extra == "extra"
Requires-Dist: polars; extra == "extra"
Requires-Dist: jupyter; extra == "extra"
Requires-Dist: matplotlib; extra == "extra"
Requires-Dist: seaborn; extra == "extra"
Requires-Dist: rdata; extra == "extra"
